cicconf/__init__.py
cicconf/cmdip.py
cicconf/command.py
cicconf/config.py
cicconf/entry.py
cicconf-0.1.9.dist-info/licenses/LICENSE
cicconf-0.1.9.dist-info/METADATA
cicconf-0.1.9.dist-info/WHEEL
cicconf-0.1.9.dist-info/entry_points.txt
cicconf-0.1.9.dist-info/top_level.txt
cicconf-0.1.9.dist-info/RECORD
