Metadata-Version: 2.4
Name: cicconf
Version: 0.1.9
Summary: Configuration and Revision tool
Home-page: https://github.com/wulffern/cicconf
Author: Carsten Wulff
Author-email: Carsten Wulff <carsten@wulff.no>
License: MIT
Project-URL: Homepage, https://github.com/wulffern/cicconf
Project-URL: Bug Tracker, https://github.com/wulffern/cicconf/issues
Classifier: Programming Language :: Python :: 3
Classifier: Intended Audience :: Science/Research
Classifier: License :: OSI Approved :: MIT License
Classifier: Operating System :: OS Independent
Requires-Python: >=3.8
License-File: LICENSE
Requires-Dist: GitPython
Requires-Dist: click
Requires-Dist: matplotlib
Requires-Dist: PyYAML
Dynamic: author
Dynamic: home-page
Dynamic: license-file
Dynamic: requires-python
